pytest_filemarker/plugin.py
pytest_filemarker-0.1.0.dev4.dist-info/LICENSE
pytest_filemarker-0.1.0.dev4.dist-info/METADATA
pytest_filemarker-0.1.0.dev4.dist-info/WHEEL
pytest_filemarker-0.1.0.dev4.dist-info/entry_points.txt
pytest_filemarker-0.1.0.dev4.dist-info/top_level.txt
pytest_filemarker-0.1.0.dev4.dist-info/RECORD
