Metadata-Version: 2.1
Name: pytest-filemarker
Version: 0.1.0.dev4
Summary: A pytest plugin that runs marked tests when files change.
Home-page: https://github.com/stickperson/pytest-filemarker
Author: Joe Meissler
Author-email: meissler.dev@gmail.com
License: MIT
Platform: UNKNOWN
Classifier: Framework :: Pytest
Requires-Python: >=3.6
Requires-Dist: pytest
